Workbook
Name Slicer_Category: #N/A
Name Slicer_Order_Status: #N/A
Name Slicer_Region: #N/A
Name Slicer_Sales_Channel: #N/A

Sheet product wise sales
A3: Row Labels | B3: Sum of Net_Sales
A4: Business Monitor 24 | B4: 970050
A5: Conference Camera | B5: 1094775
A6: Docking Station | B6: 570490
A7: Laptop Air 13 | B7: 3044200
A8: Laptop Pro 14 | B8: 4083300
A9: Office Chair | B9: 1179375
A10: Office Headset | B10: 218400
A11: Standing Desk | B11: 1494900
A12: Wireless Keyboard | B12: 93600
A13: Wireless Mouse | B13: 203040
A14: Grand Total | B14: 12952130

Sheet customer wise sales
A3: Row Labels | B3: Sum of Net_Sales
A4: Aarav Sharma | B4: 792370
A5: Aditya Jain | B5: 41675
A6: Ananya Das | B6: 840585
A7: Arjun Rao | B7: 935800
A8: Divya Iyer | B8: 1288050
A9: Ishita Roy | B9: 299840
A10: Karan Mehta | B10: 148295
A11: Kavya Menon | B11: 825130
A12: Manish Yadav | B12: 300855
A13: Meera Nair | B13: 1115510
A14: Neha Verma | B14: 1633030
A15: Nikhil Bansal | B15: 186905
... A24: Grand Total | B24: 12952130

Sheet region wise sales
A3: Row Labels | B3: Sum of Net_Sales
A4: Central | B4: 778385
A5: East | B5: 1140425
A6: North | B6: 4198890
A7: South | B7: 5648180
A8: West | B8: 1186250
A9: Grand Total | B9: 12952130

Sheet category wise profit margin
A3: Row Labels | B3: Sum of Profit Margin %
A4: Accessories | B4: 33.349861
A5: Electronics | B5: 24.704912
A6: Furniture | B6: 13.254918
A7: Grand Total | B7: 71.309691

Sheet region wise sales,profit
A3: Row Labels | B3: Sum of Net_Sales | C3: Sum of Profit | D3: Average of Profit Margin %
A4: Central | B4: 778385 | C4: 264238.2 | D4: 0.24651231
A5: East | B5: 1140425 | C5: 351826.41 | D5: 0.2460503
A6: North | B6: 4198890 | C6: 1284706.8 | D6: 0.22495752
A7: South | B7: 5648180 | C7: 1633475.4 | D7: 0.24164034
A8: West | B8: 1186250 | C8: 352984.41 | D8: 0.23890669
A9: Grand Total | B9: 12952130 | C9: 3887231.2 | D9: 0.23769897

Sheet channel wise profit,sales,order
A3: Row Labels | B3: Sum of Net_Sales | C3: Average of Profit Margin % | D3: Count of Customer_ID | E3: Sum of Profit
A4: Online | B4: 4487245 | C4: 0.23224373 | D4: 101 | E4: 1303266.8
A5: Partner | B5: 4936155 | C5: 0.24370535 | D5: 103 | E5: 1548281.6
A6: Retail | B6: 3528730 | C6: 0.236994 | D6: 96 | E6: 1035682.7
A7: Grand Total | B7: 12952130 | C7: 0.23769897 | D7: 300 | E7: 3887231.2

Sheet count of orders using pivot
A3: Count of Order_ID
A4: 300

Sheet month wise sales and profit
A3: Row Labels | B3: Sum of Net_Sales | C3: Sum of Profit
A4: Jan | B4: 798300 | C4: 271381.04
A5: Feb | B5: 1261905 | C5: 450057.49
A6: Mar | B6: 944235 | C6: 224447.75
A7: Apr | B7: 315385 | C7: 103679.98
A8: May | B8: 1651290 | C8: 510085.6
A9: Jun | B9: 957265 | C9: 245222.13
A10: Jul | B10: 1333680 | C10: 427587
A11: Aug | B11: 1200335 | C11: 335177.32
A12: Sep | B12: 955595 | C12: 305000.32
A13: Oct | B13: 790970 | C13: 235003.39
A14: Nov | B14: 1234280 | C14: 361672.17
A15: Dec | B15: 1508890 | C15: 417917.02
A16: Grand Total | B16: 12952130 | C16: 3887231.2

Sheet category wise sales
A3: Row Labels | B3: Sum of Net_Sales
A4: Accessories | B4: 1085530
A5: Electronics | B5: 9192325
A6: Furniture | B6: 2674275
A7: Grand Total | B7: 12952130

Sheet channel wise sales
A3: Row Labels | B3: Sum of Net_Sales
A4: Online | B4: 4487245
A5: Partner | B5: 4936155
A6: Retail | B6: 3528730
A7: Grand Total | B7: 12952130

Sheet sum of profit margin%
A3: Sum of Profit Margin %
A4: 71.309691

Sheet Raw_Data
A1: Order_ID | B1: Order_Date | C1: Customer_ID | D1: Customer_Name | E1: City | F1: Region | G1: Customer_Segment | H1: Product_ID | I1: Product_Name | J1: Category | K1: Subcategory | L1: Quantity | M1: Unit_Price | N1: Discount_% | O1: Gross_Sales | P1: Discount_Amount | Q1: Net_Sales | R1: Cost | S1: Profit | T1: Profit Margin % | U1: Sales_Channel | V1: Sales_Rep | W1: Payment_Method | X1: Order_Status
A2: SO10051 | B2: 45658 | C2: C013 | D2: Aditya Jain | E2: Noida | F2: North | G2: Enterprise | H2: P009 | I2: Standing Desk | J2: Furniture | K2: Desk | L2: 5 | M2: 22000 | N2: 0.05 | O2: 110000 | P2: 5500 | Q2: -104500 | R2: 65881.38 | S2: -38618.62 | T2: =IFERROR(Raw_Data!$S2/Raw_Data!$Q2,0) -> 0.36955617 | U2: Partner | V2: Sanjay | W2: Bank Transfer | X2: Returned
A3: SO10265 | B3: 45661 | C3: C016 | D3: Divya Iyer | E3: Coimbatore | F3: South | G3: SMB | H3: P001 | I3: Laptop Pro 14 | J3: Electronics | K3: Premium Laptop | L3: 7 | M3: 78000 | N3: 0 | O3: 546000 | P3: 0 | Q3: 0 | R3: 318871.79 | S3: 0 | T3: =IFERROR(Raw_Data!$S3/Raw_Data!$Q3,0) -> 0 | U3: Retail | V3: Kavita | W3: Bank Transfer | X3: Cancelled
A4: SO10229 | B4: 45662 | C4: C010 | D4: Meera Nair | E4: Kochi | F4: South | G4: SMB | H4: P001 | I4: Laptop Pro 14 | J4: Electronics | K4: Premium Laptop | L4: 5 | M4: 78000 | N4: 0.15 | O4: 390000 | P4: 58500 | Q4: 331500 | R4: 240227.41 | S4: 91272.59 | T4: =IFERROR(Raw_Data!$S4/Raw_Data!$Q4,0) -> 0.2753321 | U4: Retail | V4: Neeraj | W4: Net Banking | X4: Completed | Z4: =(SUM(Table5[Profit])/SUM(Table5[Net_Sales]))*100 -> 30.012293
A5: SO10099 | B5: 45665 | C5: C010 | D5: Meera Nair | E5: Kochi | F5: South | G5: SMB | H5: P009 | I5: Standing Desk | J5: Furniture | K5: Desk | L5: 7 | M5: 22000 | N5: 0 | O5: 154000 | P5: 0 | Q5: 154000 | R5: 97624.94 | S5: 56375.06 | T5: =IFERROR(Raw_Data!$S5/Raw_Data!$Q5,0) -> 0.36607182 | U5: Retail | V5: Ravi | W5: UPI | X5: Completed
A6: SO10231 | B6: 45665 | C6: C009 | D6: Arjun Rao | E6: Chennai | F6: South | G6: Enterprise | H6: P003 | I6: Business Monitor 24 | J6: Electronics | K6: Monitor | L6: 6 | M6: 14500 | N6: 0.05 | O6: 87000 | P6: 4350 | Q6: 82650 | R6: 59199.51 | S6: 23450.49 | T6: =IFERROR(Raw_Data!$S6/Raw_Data!$Q6,0) -> 0.28373249 | U6: Online | V6: Kavita | W6: Net Banking | X6: Completed
A7: SO10272 | B7: 45666 | C7: C006 | D7: Ananya Das | E7: Kolkata | F7: East | G7: SMB | H7: P006 | I7: Office Headset | J7: Accessories | K7: Headset | L7: 4 | M7: 4200 | N7: 0.15 | O7: 16800 | P7: 2520 | Q7: 0 | R7: 8776.57 | S7: 0 | T7: =IFERROR(Raw_Data!$S7/Raw_Data!$Q7,0) -> 0 | U7: Retail | V7: Ravi | W7: Bank Transfer | X7: Cancelled
A8: SO10149 | B8: 45667 | C8: C002 | D8: Priya Singh | E8: Mumbai | F8: West | G8: SMB | H8: P007 | I8: Docking Station | J8: Accessories | K8: Dock | L8: 8 | M8: 8900 | N8: 0 | O8: 71200 | P8: 0 | Q8: -71200 | R8: 56027.74 | S8: -15172.26 | T8: =IFERROR(Raw_Data!$S8/Raw_Data!$Q8,0) -> 0.21309354 | U8: Retail | V8: Kavita | W8: Net Banking | X8: Returned
A9: SO10021 | B9: 45668 | C9: C003 | D9: Rahul Kumar | E9: Bengaluru | F9: South | G9: Enterprise | H9: P006 | I9: Office Headset | J9: Accessories | K9: Headset | L9: 4 | M9: 4200 | N9: 0.15 | O9: 16800 | P9: 2520 | Q9: 14280 | R9: 9037.13 | S9: 5242.87 | T9: =IFERROR(Raw_Data!$S9/Raw_Data!$Q9,0) -> 0.36714776 | U9: Partner | V9: Sanjay | W9: Credit Card | X9: Completed
A10: SO10054 | B10: 45670 | C10: C007 | D10: Karan Mehta | E10: Pune | F10: West | G10: Mid-Market | H10: P003 | I10: Business Monitor 24 | J10: Electronics | K10: Monitor | L10: 1 | M10: 14500 | N10: 0 | O10: 14500 | P10: 0 | Q10: -14500 | R10: 11834.1 | S10: -2665.9 | T10: =IFERROR(Raw_Data!$S10/Raw_Data!$Q10,0) -> 0.18385517 | U10: Online | V10: Neeraj | W10: Net Banking | X10: Returned
A11: SO10141 | B11: 45672 | C11: C020 | D11: Tanya Kapoor | E11: Nagpur | F11: Central | G11: SMB | H11: P005 | I11: Wireless Mouse | J11: Accessories | K11: Mouse | L11: 3 | M11: 1800 | N11: 0.05 | O11: 5400 | P11: 270 | Q11: 5130 | R11: 3840.56 | S11: 1289.44 | T11: =IFERROR(Raw_Data!$S11/Raw_Data!$Q11,0) -> 0.25135283 | U11: Retail | V11: Amit | W11: Credit Card | X11: Completed
A12: SO10003 | B12: 45674 | C12: C019 | D12: Sahil Khan | E12: Indore | F12: Central | G12: Mid-Market | H12: P007 | I12: Docking Station | J12: Accessories | K12: Dock | L12: 1 | M12: 8900 | N12: 0 | O12: 8900 | P12: 0 | Q12: -8900 | R12: 5629.01 | S12: -3270.99 | T12: =IFERROR(Raw_Data!$S12/Raw_Data!$Q12,0) -> 0.36752697 | U12: Partner | V12: Ravi | W12: UPI | X12: Returned
A13: SO10022 | B13: 45674 | C13: C008 | D13: Neha Verma | E13: Jaipur | F13: North | G13: SMB | H13: P002 | I13: Laptop Air 13 | J13: Electronics | K13: Standard Laptop | L13: 6 | M13: 62000 | N13: 0 | O13: 372000 | P13: 0 | Q13: 372000 | R13: 261663.86 | S13: 110336.14 | T13: =IFERROR(Raw_Data!$S13/Raw_Data!$Q13,0) -> 0.29660253 | U13: Partner | V13: Neeraj | W13: UPI | X13: Completed
A14: SO10189 | B14: 45674 | C14: C013 | D14: Aditya Jain | E14: Noida | F14: North | G14: Enterprise | H14: P010 | I14: Conference Camera | J14: Electronics | K14: Camera | L14: 3 | M14: 16500 | N14: 0.2 | O14: 49500 | P14: 9900 | Q14: 39600 | R14: 27244.06 | S14: 12355.94 | T14: =IFERROR(Raw_Data!$S14/Raw_Data!$Q14,0) -> 0.31201869 | U14: Retail | V14: Neeraj | W14: Credit Card | X14: Completed
A15: SO10218 | B15: 45674 | C15: C005 | D15: Vikram Patel | E15: Ahmedabad | F15: West | G15: Mid-Market | H15: P004 | I15: Wireless Keyboard | J15: Accessories | K15: Keyboard | L15: 2 | M15: 3200 | N15: 0 | O15: 6400 | P15: 0 | Q15: 6400 | R15: 3741.09 | S15: 2658.91 | T15: =IFERROR(Raw_Data!$S15/Raw_Data!$Q15,0) -> 0.41545469 | U15: Retail | V15: Sneha | W15: Net Banking | X15: Completed
A16: SO10242 | B16: 45674 | C16: C003 | D16: Rahul Kumar | E16: Bengaluru | F16: South | G16: Enterprise | H16: P008 | I16: Office Chair | J16: Furniture | K16: Chair | L16: 5 | M16: 12500 | N16: 0.1 | O16: 62500 | P16: 6250 | Q16: 56250 | R16: 35054.75 | S16: 21195.25 | T16: =IFERROR(Raw_Data!$S16/Raw_Data!$Q16,0) -> 0.37680444 | U16: Partner | V16: Sanjay | W16: Net Banking | X16: Completed
... A301: SO10163 | B301: 46020 | C301: C005 | D301: Vikram Patel | E301: Ahmedabad | F301: West | G301: Mid-Market | H301: P010 | I301: Conference Camera | J301: Electronics | K301: Camera | L301: 2 | M301: 16500 | N301: 0.05 | O301: 33000 | P301: 1650 | Q301: 0 | R301: 22388.33 | S301: 0 | T301: =IFERROR(Raw_Data!$S301/Raw_Data!$Q301,0) -> 0 | U301: Retail | V301: Sneha | W301: Credit Card | X301: Cancelled
V307: {=_xlfn.UNIQUE(X:X)} -> Order_Status
Q308: =_xlfn.XLOOKUP(H296,Raw_Data!$H$2:$H$301,Raw_Data!$M$2:$M$301) -> 1800 | V308: Returned
M309: =COUNTIF(N:N,"<0")+COUNTIF(N:N,"">1) -> 0 | V309: Cancelled
V310: Completed
V311: 0

Sheet Customer_Master
A1: Customer_ID | B1: Customer_Name | C1: City | D1: Region | E1: Customer_Segment
A2: C001 | B2: Aarav Sharma | C2: Delhi | D2: North | E2: Enterprise
A3: C002 | B3: Priya Singh | C3: Mumbai | D3: West | E3: SMB
A4: C003 | B4: Rahul Kumar | C4: Bengaluru | D4: South | E4: Enterprise
A5: C004 | B5: Sneha Reddy | C5: Hyderabad | D5: South | E5: SMB
A6: C005 | B6: Vikram Patel | C6: Ahmedabad | D6: West | E6: Mid-Market
A7: C006 | B7: Ananya Das | C7: Kolkata | D7: East | E7: SMB
A8: C007 | B8: Karan Mehta | C8: Pune | D8: West | E8: Mid-Market
A9: C008 | B9: Neha Verma | C9: Jaipur | D9: North | E9: SMB
A10: C009 | B10: Arjun Rao | C10: Chennai | D10: South | E10: Enterprise
A11: C010 | B11: Meera Nair | C11: Kochi | D11: South | E11: SMB
A12: C011 | B12: Rohan Gupta | C12: Lucknow | D12: North | E12: Mid-Market
... A21: C020 | B21: Tanya Kapoor | C21: Nagpur | D21: Central | E21: SMB

Sheet Product_Master
A1: Product_ID | B1: Product_Name | C1: Category | D1: Subcategory | E1: Unit_Price
A2: P001 | B2: Laptop Pro 14 | C2: Electronics | D2: Premium Laptop | E2: 78000
A3: P002 | B3: Laptop Air 13 | C3: Electronics | D3: Standard Laptop | E3: 62000
A4: P003 | B4: Business Monitor 24 | C4: Electronics | D4: Monitor | E4: 14500
A5: P004 | B5: Wireless Keyboard | C5: Accessories | D5: Keyboard | E5: 3200
A6: P005 | B6: Wireless Mouse | C6: Accessories | D6: Mouse | E6: 1800
A7: P006 | B7: Office Headset | C7: Accessories | D7: Headset | E7: 4200
A8: P007 | B8: Docking Station | C8: Accessories | D8: Dock | E8: 8900
A9: P008 | B9: Office Chair | C9: Furniture | D9: Chair | E9: 12500
A10: P009 | B10: Standing Desk | C10: Furniture | D10: Desk | E10: 22000
A11: P010 | B11: Conference Camera | C11: Electronics | D11: Camera | E11: 16500

Sheet Sales dashboard
A4: KPI | B4: Value
A5: Total Net Sales | B5: =SUM(Table5[Net_Sales]) -> 12952130
A6: Total Profit | B6: =SUM(Table5[Profit]) -> 3887231.2
A7: Total Orders | B7: =COUNTA(Table5[Order_ID]) -> 300
A8: Profit Margin % | B8: =IFERROR(B6/B5,0) -> 0.30012293
